ipy2d/__init__.py
ipy2d/__main__.py
ipy2d/convert.py
ipy2d/fun.py
ipy2d/pil.py
ipy2d-0.1.0.dist-info/LICENSE
ipy2d-0.1.0.dist-info/METADATA
ipy2d-0.1.0.dist-info/WHEEL
ipy2d-0.1.0.dist-info/top_level.txt
ipy2d-0.1.0.dist-info/RECORD
