Metadata-Version: 2.1
Name: ipy2d
Version: 0.1.0
Summary: Convert IP addresses to integers
Home-page: https://github.com/0xflotus/ipy2d
Author: 0xflotus
Author-email: 0xflotus+pypi@gmail.com
License: MIT
Platform: UNKNOWN
Classifier: License :: OSI Approved :: MIT License
Classifier: Programming Language :: Python :: 3
Classifier: Programming Language :: Python :: 3.9
License-File: LICENSE
Requires-Dist: netaddr
